{
	"id": "vendora-api-environment",
	"name": "Vendora API - Local",
	"values": [
		{
			"key": "baseUrl",
			"value": "http://localhost:3000",
			"type": "default",
			"enabled": true
		},
		{
			"key": "bearerToken",
			"value": "",
			"type": "secret",
			"enabled": true
		},
		{
			"key": "refreshToken",
			"value": "",
			"type": "secret",
			"enabled": true
		},
		{
			"key": "userId",
			"value": "",
			"type": "default",
			"enabled": true
		},
		{
			"key": "organizationId",
			"value": "",
			"type": "default",
			"enabled": true
		},
		{
			"key": "factoryId",
			"value": "",
			"type": "default",
			"enabled": true
		},
		{
			"key": "productId",
			"value": "",
			"type": "default",
			"enabled": true
		},
		{
			"key": "variantId",
			"value": "",
			"type": "default",
			"enabled": true
		},
		{
			"key": "orderId",
			"value": "",
			"type": "default",
			"enabled": true
		}
	],
	"_postman_variable_scope": "environment"
}
